nlgserv
