Metadata-Version: 1.0
Name: nlgserv
Version: 0.2.1
Summary: JSON HTTP wrapper for SimpleNLG
Home-page: UNKNOWN
Author: Darren Richardson
Author-email: UNKNOWN
License: LICENSE.txt
Platform: UNKNOWN
